.gitignore
LICENSE.txt
README.rst
logging.yaml
requirements.txt
setup.cfg
setup.py
version.py
bin/arp
bin/fakeAP README.md
bin/fakeAP.py
bin/fakeap
bin/proxy
bin/proxy1
bin/users
mim/__init__.py
mim/proxyclient.py
mim/proxyserver.py
mim.egg-info/PKG-INFO
mim.egg-info/SOURCES.txt
mim.egg-info/dependency_links.txt
mim.egg-info/requires.txt
mim.egg-info/top_level.txt
mim/plugins/__init__.py
mim/plugins/favicon.py
mim/plugins/logrequests.py
mim/plugins/otherplugins.py
mim/plugins/sslstrip.py
mim/plugins/data/cats.jpg
mim/plugins/data/injection.html
mim/plugins/data/lock.ico
mim/tools/__init__.py
mim/tools/bash.py
mim/tools/fileserver.py
mim/tools/pydispatch2.py
mim/tools/tools.py