Metadata-Version: 1.1
Name: mim
Version: 0.2.42
Summary: Man in the middle proxy server
Home-page: https://github.com/simonm3/mim
Author: simon
Author-email: simonm3@gmail.com
License: GNU General Public License v2 (GPLv2)
Platform: UNKNOWN
Classifier: Development Status :: 4 - Beta
Classifier: Environment :: Console
Classifier: Operating System :: POSIX :: Linux
Classifier: Programming Language :: Python
